{
  "generatedAt": "2026-06-02T19:36:50.490Z",
  "status": "passed",
  "assets": [
    {
      "fileName": "neon-lane-dash-icon-512.png",
      "width": 512,
      "height": 512
    },
    {
      "fileName": "neon-lane-dash-cover-16x9.png",
      "width": 1280,
      "height": 720
    },
    {
      "fileName": "neon-lane-dash-crazygames-landscape-1920x1080.png",
      "width": 1920,
      "height": 1080
    },
    {
      "fileName": "neon-lane-dash-crazygames-portrait-800x1200.png",
      "width": 800,
      "height": 1200
    },
    {
      "fileName": "neon-lane-dash-playgama-portrait-1080x1920.png",
      "width": 1080,
      "height": 1920
    },
    {
      "fileName": "neon-lane-dash-crazygames-square-800x800.png",
      "width": 800,
      "height": 800
    },
    {
      "fileName": "neon-lane-dash-social-card.png",
      "width": 1200,
      "height": 630
    }
  ],
  "failures": []
}
